{
  "@context": "http://iiif.io/api/image/2/context.json",
  "@id": "https://sjsu-library.github.io/unionist/img/derivatives/iiif/images/unionist--image-0319",
  "protocol": "http://iiif.io/api/image",
  "width": 456,
  "height": 274,
  "sizes": [
    {
      "width": 456,
      "height": 274
    },
    {
      "width": 250,
      "height": 150
    },
    {
      "width": 1140,
      "height": 685
    }
  ],
  "profile": [
    "http://iiif.io/api/image/2/level0.json",
    {
      "supports": [
        "cors",
        "sizeByWhListed",
        "baseUriRedirect"
      ]
    }
  ],
  "tiles": [
    {
      "width": 512,
      "scaleFactors": [
        1,
        2,
        4,
        8
      ]
    }
  ]
}
